pyseasnve/__init__.py
pyseasnve/constants.py
pyseasnve/consumption.py
pyseasnve/core.py
pyseasnve/exceptions.py
pyseasnve/forecast.py
pyseasnve/helpers.py
pyseasnve/pyseasnve.py
pyseasnve-0.2.0.dist-info/AUTHORS.rst
pyseasnve-0.2.0.dist-info/LICENSE
pyseasnve-0.2.0.dist-info/METADATA
pyseasnve-0.2.0.dist-info/WHEEL
pyseasnve-0.2.0.dist-info/top_level.txt
pyseasnve-0.2.0.dist-info/RECORD
