Metadata-Version: 2.1
Name: pyseasnve
Version: 0.2.0
Summary: An unofficial class to interact with the Seas-NVE API
Home-page: https://github.com/magnuslarsen/pyseasnve
Author: Magnus Larsen
Author-email: magnusfynbo@hotmail.com
License: GNU General Public License v3
Keywords: pyseasnve
Platform: UNKNOWN
Classifier: Development Status :: 2 - Pre-Alpha
Classifier: Intended Audience :: Developers
Classifier: License :: OSI Approved :: GNU General Public License v3 (GPLv3)
Classifier: Natural Language :: English
Classifier: Programming Language :: Python :: 3
Classifier: Programming Language :: Python :: 3.6
Classifier: Programming Language :: Python :: 3.7
Classifier: Programming Language :: Python :: 3.8
Requires-Python: >=3.6
License-File: LICENSE
License-File: AUTHORS.rst
Requires-Dist: requests (>=2.7)
Requires-Dist: pytz (>=2021.3)
